CHANGES.txt
LICENSE
MANIFEST.in
README.md
setup.py
frl/__init__.py
frl/client.py
frl/server.py
frl.egg-info/PKG-INFO
frl.egg-info/SOURCES.txt
frl.egg-info/dependency_links.txt
frl.egg-info/not-zip-safe
frl.egg-info/requires.txt
frl.egg-info/top_level.txt