Metadata-Version: 1.1
Name: frl
Version: 0.0.4
Summary: flask/requests logging
Home-page: UNKNOWN
Author: Balanced
Author-email: dev+frl@balancedpayments.com
License: The MIT License: http://www.opensource.org/licenses/mit-license.php
Platform: UNKNOWN
Classifier: Programming Language :: Python
Classifier: License :: OSI Approved :: MIT License
